biocsetup/__init__.py
biocsetup/cli.py
biocsetup/create_repository.py
biocsetup/templates/github_workflows/publish-pypi.yml
biocsetup/templates/github_workflows/run-tests.yml
biocsetup/templates/precommit/pre-commit-config.yaml
biocsetup-0.3.1.dist-info/licenses/LICENSE.txt
biocsetup-0.3.1.dist-info/METADATA
biocsetup-0.3.1.dist-info/WHEEL
biocsetup-0.3.1.dist-info/entry_points.txt
biocsetup-0.3.1.dist-info/top_level.txt
biocsetup-0.3.1.dist-info/RECORD
