Metadata-Version: 2.4
Name: biocsetup
Version: 0.3.1
Summary: "A CLI interface to quickly scaffold new BiocPy Python packages"
Home-page: https://github.com/biocpy/biocsetup
Author: Jayaram Kancherla
Author-email: jayaram.kancherla@gmail.com
License: MIT
Project-URL: Documentation, https://github.com/biocpy/biocsetup
Project-URL: Source, https://github.com/biocpy/biocsetup
Platform: any
Classifier: Development Status :: 4 - Beta
Classifier: Programming Language :: Python
Requires-Python: >=3.9
License-File: LICENSE.txt
Requires-Dist: importlib-metadata; python_version < "3.8"
Requires-Dist: pyscaffold>=4.0
Requires-Dist: pyscaffoldext-markdown
Requires-Dist: click>=8.0
Provides-Extra: testing
Requires-Dist: setuptools; extra == "testing"
Requires-Dist: pytest; extra == "testing"
Requires-Dist: pytest-cov; extra == "testing"
Dynamic: license-file
